<?xml version='1.0' encoding='UTF-8'?>
<xmi:XMI xmlns:xmi="http://www.omg.org/spec/XMI/20131001" xmi:version="2.1"><xmi:Extension extender="Enterprise Architect"><elements><element xmi:type="uml:Class" xmi:idref="_MH8ldE3jEfGtk7c49LZMNg" name="hariTerm:Class"><properties /><attributes /></element><element xmi:type="uml:Class" xmi:idref="_MH8li03jEfGtk7c49LZMNg" name="hariTerm:Datatype"><properties /><attributes /></element><element xmi:type="uml:Class" xmi:idref="_MH8ljU3jEfGtk7c49LZMNg" name="hariTerm:Property"><properties stereotype="Abstract" /><attributes><attribute xmi:idref="_MH8lkk3jEfGtk7c49LZMNg" name="hariTerm:isTransitive"><properties type="xsd:boolean" /><bounds lower="1" upper="1" /></attribute><attribute xmi:idref="_MH8lk03jEfGtk7c49LZMNg" name="hariTerm:isSymmetric"><properties type="xsd:boolean" /><bounds lower="1" upper="1" /></attribute><attribute xmi:idref="_MH8llE3jEfGtk7c49LZMNg" name="hariTerm:isFunctional"><properties type="xsd:boolean" /><bounds lower="1" upper="1" /></attribute><attribute xmi:idref="_MH8llU3jEfGtk7c49LZMNg" name="hariTerm:isInverseFunctional"><properties type="xsd:boolean" /><bounds lower="1" upper="1" /></attribute><attribute xmi:idref="_MH8llk3jEfGtk7c49LZMNg" name="hariTerm:isAssymetric"><properties type="xsd:boolean" /><bounds lower="1" upper="1" /></attribute><attribute xmi:idref="_MH8ll03jEfGtk7c49LZMNg" name="hariTerm:isReflexive"><properties type="xsd:boolean" /><bounds lower="1" upper="1" /></attribute><attribute xmi:idref="_MH8lmE3jEfGtk7c49LZMNg" name="hariTerm:isIrreflexive"><properties type="xsd:boolean" /><bounds lower="1" upper="1" /></attribute></attributes></element><element xmi:type="uml:Class" xmi:idref="_MH8lnU3jEfGtk7c49LZMNg" name="hariTerm:DatatypeProperty"><properties /><attributes /></element><element xmi:type="uml:Class" xmi:idref="_MH8lqU3jEfGtk7c49LZMNg" name="hariTerm:ObjectProperty"><properties /><attributes /></element><element xmi:type="uml:Class" xmi:idref="_MH8lwE3jEfGtk7c49LZMNg" name="hariTerm:AnotationProperty"><properties /><attributes /></element><element xmi:type="uml:Class" xmi:idref="_MH8lx03jEfGtk7c49LZMNg" name="hariTerm:OntologicalTerm"><properties stereotype="Abstract" /><attributes><attribute xmi:idref="_MH8lyE3jEfGtk7c49LZMNg" name="hariTerm:hasTermIRI"><properties type="xsd:string" /><bounds lower="1" upper="1" /></attribute><attribute xmi:idref="_MH8lyU3jEfGtk7c49LZMNg" name="hariTerm:hasTermLabel"><properties type="xsd:string" /><bounds lower="1" upper="1" /></attribute><attribute xmi:idref="_MH8lyk3jEfGtk7c49LZMNg" name="hariTerm:hasTermDefinition"><properties type="xsd:string" /><bounds lower="1" upper="1" /></attribute><attribute xmi:idref="_MH8ly03jEfGtk7c49LZMNg" name="hariTerm:hasTermExample"><properties type="xsd:string" /><bounds lower="0" upper="*" /></attribute></attributes></element><element xmi:type="uml:Class" xmi:idref="_MH8lzk3jEfGtk7c49LZMNg" name="hariTerm:Types"><properties stereotype="Abstract" /><attributes /></element></elements><connectors><connector xmi:idref="auto_gen_thing__MH8lx03jEfGtk7c49LZMNg"><properties ea_type="Generalization" direction="Source -&gt; Destination" /><source xmi:idref="_MH8lx03jEfGtk7c49LZMNg"><model name="hariTerm:OntologicalTerm" type="Class" /></source><target xmi:idref="http://www.w3.org/2002/07/owl#Thing"><model name="owl:Thing" type="Class" /></target></connector><connector xmi:idref="_MH8lf03jEfGtk7c49LZMNg"><properties ea_type="Association" direction="Source -&gt; Destination" /><source xmi:idref="_MH8ldE3jEfGtk7c49LZMNg"><model name="hariTerm:Class" type="Class" /></source><target xmi:idref="_MH8ldE3jEfGtk7c49LZMNg"><model name="hariTerm:Class" type="Class" /><type multiplicity="0..*" /><role name="hariTerm:hasSubClassOf" visibility="Public" /></target></connector><connector xmi:idref="_MH8lg03jEfGtk7c49LZMNg"><properties ea_type="Association" direction="Source -&gt; Destination" /><source xmi:idref="_MH8ldE3jEfGtk7c49LZMNg"><model name="hariTerm:Class" type="Class" /></source><target xmi:idref="_MH8ldE3jEfGtk7c49LZMNg"><model name="hariTerm:Class" type="Class" /><type multiplicity="0..*" /><role name="hariTerm:hasDisjointWith" visibility="Public" /></target></connector><connector xmi:idref="_MH8lh03jEfGtk7c49LZMNg"><properties ea_type="Association" direction="Source -&gt; Destination" /><source xmi:idref="_MH8ldE3jEfGtk7c49LZMNg"><model name="hariTerm:Class" type="Class" /></source><target xmi:idref="_MH8ldE3jEfGtk7c49LZMNg"><model name="hariTerm:Class" type="Class" /><type multiplicity="0..*" /><role name="hariTerm:hasEquivalentTo" visibility="Public" /></target></connector><connector xmi:idref="_MH8lmU3jEfGtk7c49LZMNg"><properties ea_type="Association" direction="Source -&gt; Destination" /><source xmi:idref="_MH8ljU3jEfGtk7c49LZMNg"><model name="hariTerm:Property" type="Class" /></source><target xmi:idref="_MH8ljU3jEfGtk7c49LZMNg"><model name="hariTerm:Property" type="Class" /><type multiplicity="0..*" /><role name="hariTerm:hasSubPropertyOf" visibility="Public" /></target></connector><connector xmi:idref="_MH8loU3jEfGtk7c49LZMNg"><properties ea_type="Association" direction="Source -&gt; Destination" /><source xmi:idref="_MH8lnU3jEfGtk7c49LZMNg"><model name="hariTerm:DatatypeProperty" type="Class" /></source><target xmi:idref="_MH8ldE3jEfGtk7c49LZMNg"><model name="hariTerm:Class" type="Class" /><type multiplicity="1..1" /><role name="hariTerm:hasDomainDatatype" visibility="Public" /></target></connector><connector xmi:idref="_MH8lpU3jEfGtk7c49LZMNg"><properties ea_type="Association" direction="Source -&gt; Destination" /><source xmi:idref="_MH8lnU3jEfGtk7c49LZMNg"><model name="hariTerm:DatatypeProperty" type="Class" /></source><target xmi:idref="_MH8li03jEfGtk7c49LZMNg"><model name="hariTerm:Datatype" type="Class" /><type multiplicity="1..1" /><role name="hariTerm:hasRangeDatatype" visibility="Public" /></target></connector><connector xmi:idref="_MH8lsk3jEfGtk7c49LZMNg"><properties ea_type="Association" direction="Source -&gt; Destination" /><source xmi:idref="_MH8lqU3jEfGtk7c49LZMNg"><model name="hariTerm:ObjectProperty" type="Class" /></source><target xmi:idref="_MH8ldE3jEfGtk7c49LZMNg"><model name="hariTerm:Class" type="Class" /><type multiplicity="1..1" /><role name="hariTerm:hasDomainClass" visibility="Public" /></target></connector><connector xmi:idref="_MH8ltk3jEfGtk7c49LZMNg"><properties ea_type="Association" direction="Source -&gt; Destination" /><source xmi:idref="_MH8lqU3jEfGtk7c49LZMNg"><model name="hariTerm:ObjectProperty" type="Class" /></source><target xmi:idref="_MH8ldE3jEfGtk7c49LZMNg"><model name="hariTerm:Class" type="Class" /><type multiplicity="1..1" /><role name="hariTerm:hasRangeClass" visibility="Public" /></target></connector><connector xmi:idref="_MH8luk3jEfGtk7c49LZMNg"><properties ea_type="Association" direction="Source -&gt; Destination" /><source xmi:idref="_MH8lqU3jEfGtk7c49LZMNg"><model name="hariTerm:ObjectProperty" type="Class" /></source><target xmi:idref="_MH8lqU3jEfGtk7c49LZMNg"><model name="hariTerm:ObjectProperty" type="Class" /><type multiplicity="0..1" /><role name="hariTerm:hasInverseOf" visibility="Public" /></target></connector><connector xmi:idref="_MH8lvE3jEfGtk7c49LZMNg"><properties ea_type="Association" direction="Source -&gt; Destination" /><source xmi:idref="_MH8lqU3jEfGtk7c49LZMNg"><model name="hariTerm:ObjectProperty" type="Class" /></source><target xmi:idref="_MH8lqU3jEfGtk7c49LZMNg"><model name="hariTerm:ObjectProperty" type="Class" /><type multiplicity="0..*" /><role name="hariTerm:hasPropertyChain" visibility="Public" /></target></connector><connector xmi:idref="_MH8lw03jEfGtk7c49LZMNg"><properties ea_type="Association" direction="Source -&gt; Destination" /><source xmi:idref="_MH8lwE3jEfGtk7c49LZMNg"><model name="hariTerm:AnotationProperty" type="Class" /></source><target xmi:idref="_MH8lx03jEfGtk7c49LZMNg"><model name="hariTerm:OntologicalTerm" type="Class" /><type multiplicity="1..1" /><role name="hariTerm:hasDomainAnotation" visibility="Public" /></target></connector><connector xmi:idref="_MH8ldU3jEfGtk7c49LZMNg"><properties ea_type="Generalization" direction="Source -&gt; Destination" /><source xmi:idref="_MH8ldE3jEfGtk7c49LZMNg"><model name="hariTerm:Class" type="Class" /></source><target xmi:idref="_MH8lzk3jEfGtk7c49LZMNg"><model name="hariTerm:Types" type="Class" /></target></connector><connector xmi:idref="_MH8ljE3jEfGtk7c49LZMNg"><properties ea_type="Generalization" direction="Source -&gt; Destination" /><source xmi:idref="_MH8li03jEfGtk7c49LZMNg"><model name="hariTerm:Datatype" type="Class" /></source><target xmi:idref="_MH8lzk3jEfGtk7c49LZMNg"><model name="hariTerm:Types" type="Class" /></target></connector><connector xmi:idref="_MH8ljk3jEfGtk7c49LZMNg"><properties ea_type="Generalization" direction="Source -&gt; Destination" /><source xmi:idref="_MH8ljU3jEfGtk7c49LZMNg"><model name="hariTerm:Property" type="Class" /></source><target xmi:idref="_MH8lx03jEfGtk7c49LZMNg"><model name="hariTerm:OntologicalTerm" type="Class" /></target></connector><connector xmi:idref="_MH8lnk3jEfGtk7c49LZMNg"><properties ea_type="Generalization" direction="Source -&gt; Destination" /><source xmi:idref="_MH8lnU3jEfGtk7c49LZMNg"><model name="hariTerm:DatatypeProperty" type="Class" /></source><target xmi:idref="_MH8ljU3jEfGtk7c49LZMNg"><model name="hariTerm:Property" type="Class" /></target></connector><connector xmi:idref="_MH8lqk3jEfGtk7c49LZMNg"><properties ea_type="Generalization" direction="Source -&gt; Destination" /><source xmi:idref="_MH8lqU3jEfGtk7c49LZMNg"><model name="hariTerm:ObjectProperty" type="Class" /></source><target xmi:idref="_MH8ljU3jEfGtk7c49LZMNg"><model name="hariTerm:Property" type="Class" /></target></connector><connector xmi:idref="_MH8lwU3jEfGtk7c49LZMNg"><properties ea_type="Generalization" direction="Source -&gt; Destination" /><source xmi:idref="_MH8lwE3jEfGtk7c49LZMNg"><model name="hariTerm:AnotationProperty" type="Class" /></source><target xmi:idref="_MH8ljU3jEfGtk7c49LZMNg"><model name="hariTerm:Property" type="Class" /></target></connector><connector xmi:idref="_MH8lz03jEfGtk7c49LZMNg"><properties ea_type="Generalization" direction="Source -&gt; Destination" /><source xmi:idref="_MH8lzk3jEfGtk7c49LZMNg"><model name="hariTerm:Types" type="Class" /></source><target xmi:idref="_MH8lx03jEfGtk7c49LZMNg"><model name="hariTerm:OntologicalTerm" type="Class" /></target></connector></connectors></xmi:Extension></xmi:XMI>