<?xml version='1.0' encoding='UTF-8'?>
<xmi:XMI xmlns:xmi="http://www.omg.org/spec/XMI/20131001" xmi:version="2.1"><xmi:Extension extender="Enterprise Architect"><elements><element xmi:type="uml:Class" xmi:idref="ID_AUTO_GENERATED_THING_ROOT" name="hari:Thing"><properties documentation="Clase raíz del metamodelo. Todas las clases diseñadas cuelgan de aquí." /></element><element xmi:type="uml:Class" xmi:idref="_-LuRhDJfEfGnvNG6iGafTQ" name="hari:OntologyVersion"><properties /><attributes><attribute xmi:idref="_-LuRkzJfEfGnvNG6iGafTQ" name="hari:hasVersionIRI"><properties type="xsd:string" /><bounds lower="1" upper="1" /></attribute><attribute xmi:idref="_-LuRlDJfEfGnvNG6iGafTQ" name="hari:hasVersionInfo"><properties type="xsd:string" /><bounds lower="1" upper="1" /></attribute><attribute xmi:idref="_-LuRlTJfEfGnvNG6iGafTQ" name="hari:hasKnowledgeDomain"><properties type="xsd:string" /><bounds lower="0" upper="*" /></attribute><attribute xmi:idref="_-LuRmDJfEfGnvNG6iGafTQ" name="hari:hasPriorVersionIRI"><properties type="xsd:string" /><bounds lower="0" upper="1" /></attribute></attributes></element><element xmi:type="uml:Class" xmi:idref="_-L3bejJfEfGnvNG6iGafTQ" name="hari:VersionChange"><properties stereotype="Abstract" /><attributes><attribute xmi:idref="_-L3bezJfEfGnvNG6iGafTQ" name="hari:hasDate"><properties type="xsd:date" /><bounds lower="1" upper="1" /></attribute></attributes></element><element xmi:type="uml:Class" xmi:idref="_-L3bfDJfEfGnvNG6iGafTQ" name="hari:CardinalityModification"><properties /><attributes><attribute xmi:idref="_-L3bfjJfEfGnvNG6iGafTQ" name="hari:hasPropertyIRI"><properties type="xsd:string" /><bounds lower="1" upper="1" /></attribute><attribute xmi:idref="_-L3bfzJfEfGnvNG6iGafTQ" name="hari:hasOldMin"><properties type="xsd:integer" /><bounds lower="1" upper="1" /></attribute><attribute xmi:idref="_-L3bgDJfEfGnvNG6iGafTQ" name="hari:hasOldMax"><properties type="xsd:integer" /><bounds lower="1" upper="1" /></attribute><attribute xmi:idref="_-L3bgTJfEfGnvNG6iGafTQ" name="hari:hasNewMin"><properties type="xsd:integer" /><bounds lower="1" upper="1" /></attribute><attribute xmi:idref="_-L3bgjJfEfGnvNG6iGafTQ" name="hari:hasNewMax"><properties type="xsd:integer" /><bounds lower="1" upper="1" /></attribute></attributes></element><element xmi:type="uml:Class" xmi:idref="_-L3bgzJfEfGnvNG6iGafTQ" name="hari:AttributeAddition"><properties /><attributes><attribute xmi:idref="_-L3bhTJfEfGnvNG6iGafTQ" name="hari:hasNewPropertyIRI"><properties type="xsd:string" /><bounds lower="1" upper="1" /></attribute></attributes></element><element xmi:type="uml:Class" xmi:idref="_-L3bhjJfEfGnvNG6iGafTQ" name="hari:ExtensionDecision"><properties stereotype="Abstract" /><attributes><attribute xmi:idref="_-L3biTJfEfGnvNG6iGafTQ" name="hari:hasJustificacion"><properties type="xsd:string" /><bounds lower="0" upper="1" /></attribute></attributes></element><element xmi:type="uml:Class" xmi:idref="_-L3bjzJfEfGnvNG6iGafTQ" name="hari:DirectReuseDecision"><properties stereotype="Abstract" /><attributes><attribute xmi:idref="_-L3bkDJfEfGnvNG6iGafTQ" name="hari:hasReason"><properties type="xsd:string" /><bounds lower="1" upper="1" /></attribute></attributes></element><element xmi:type="uml:Enumeration" xmi:idref="_-L3bkTJfEfGnvNG6iGafTQ" name="hari:Status"><properties /><attributes><attribute xmi:idref="_-L3bkjJfEfGnvNG6iGafTQ" name="hari:Draft"><properties type="xsd:string" /><bounds lower="1" upper="1" /></attribute><attribute xmi:idref="_-L3bkzJfEfGnvNG6iGafTQ" name="hari:Stable"><properties type="xsd:string" /><bounds lower="1" upper="1" /></attribute><attribute xmi:idref="_-L3blDJfEfGnvNG6iGafTQ" name="hari:Obsolete"><properties type="xsd:string" /><bounds lower="1" upper="1" /></attribute></attributes></element><element xmi:type="uml:Enumeration" xmi:idref="_-L3blTJfEfGnvNG6iGafTQ" name="hari:Level"><properties /><attributes><attribute xmi:idref="_-L3bljJfEfGnvNG6iGafTQ" name="hari:Foundational"><properties type="xsd:string" /><bounds lower="1" upper="1" /></attribute><attribute xmi:idref="_-L3blzJfEfGnvNG6iGafTQ" name="hari:Core"><properties type="xsd:string" /><bounds lower="1" upper="1" /></attribute><attribute xmi:idref="_-L3bmDJfEfGnvNG6iGafTQ" name="hari:Domain"><properties type="xsd:string" /><bounds lower="1" upper="1" /></attribute><attribute xmi:idref="_-L3bmTJfEfGnvNG6iGafTQ" name="hari:Application"><properties type="xsd:string" /><bounds lower="1" upper="1" /></attribute></attributes></element><element xmi:type="uml:Class" xmi:idref="_-L3bmjJfEfGnvNG6iGafTQ" name="hari:OntologyProject"><properties /><attributes><attribute xmi:idref="_-L3bnDJfEfGnvNG6iGafTQ" name="hari:hasTitle"><properties type="xsd:string" /><bounds lower="1" upper="1" /></attribute><attribute xmi:idref="_-L3bnTJfEfGnvNG6iGafTQ" name="hari:hasAcronym"><properties type="xsd:string" /><bounds lower="1" upper="1" /></attribute><attribute xmi:idref="_-L3bnjJfEfGnvNG6iGafTQ" name="hari:hasOrganization"><properties type="xsd:string" /><bounds lower="1" upper="1" /></attribute><attribute xmi:idref="_-L3bnzJfEfGnvNG6iGafTQ" name="hari:hasDescription"><properties type="xsd:string" /><bounds lower="1" upper="1" /></attribute><attribute xmi:idref="_-L3boDJfEfGnvNG6iGafTQ" name="hari:hasOntologyIRI"><properties type="xsd:string" /><bounds lower="1" upper="1" /></attribute></attributes></element><element xmi:type="uml:Class" xmi:idref="_-L3bpTJfEfGnvNG6iGafTQ" name="hari:SemanticExtension"><properties /><attributes /></element><element xmi:type="uml:Class" xmi:idref="_-L3bpzJfEfGnvNG6iGafTQ" name="hari:ExternalTerm"><properties /><attributes /></element><element xmi:type="uml:Class" xmi:idref="_-L3bqDJfEfGnvNG6iGafTQ" name="hari:CardinalityExtension"><properties /><attributes /></element><element xmi:type="uml:Class" xmi:idref="_-L3brTJfEfGnvNG6iGafTQ" name="hari:AttributeExtension"><properties /><attributes /></element><element xmi:type="uml:Class" xmi:idref="_-L3bsjJfEfGnvNG6iGafTQ" name="hari:ClassReuse"><properties /><attributes /></element><element xmi:type="uml:Class" xmi:idref="_-L3btzJfEfGnvNG6iGafTQ" name="hari:PropertyReuse"><properties /><attributes /></element></elements><connectors><connector xmi:idref="auto_gen_thing__-LuRhDJfEfGnvNG6iGafTQ"><properties ea_type="Generalization" direction="Source -&gt; Destination" /><source xmi:idref="_-LuRhDJfEfGnvNG6iGafTQ"><model name="hari:OntologyVersion" type="Class" /></source><target xmi:idref="ID_AUTO_GENERATED_THING_ROOT"><model name="hari:Thing" type="Class" /></target></connector><connector xmi:idref="auto_gen_thing__-L3bejJfEfGnvNG6iGafTQ"><properties ea_type="Generalization" direction="Source -&gt; Destination" /><source xmi:idref="_-L3bejJfEfGnvNG6iGafTQ"><model name="hari:VersionChange" type="Class" /></source><target xmi:idref="ID_AUTO_GENERATED_THING_ROOT"><model name="hari:Thing" type="Class" /></target></connector><connector xmi:idref="auto_gen_thing__-L3bhjJfEfGnvNG6iGafTQ"><properties ea_type="Generalization" direction="Source -&gt; Destination" /><source xmi:idref="_-L3bhjJfEfGnvNG6iGafTQ"><model name="hari:ExtensionDecision" type="Class" /></source><target xmi:idref="ID_AUTO_GENERATED_THING_ROOT"><model name="hari:Thing" type="Class" /></target></connector><connector xmi:idref="auto_gen_thing__-L3bjzJfEfGnvNG6iGafTQ"><properties ea_type="Generalization" direction="Source -&gt; Destination" /><source xmi:idref="_-L3bjzJfEfGnvNG6iGafTQ"><model name="hari:DirectReuseDecision" type="Class" /></source><target xmi:idref="ID_AUTO_GENERATED_THING_ROOT"><model name="hari:Thing" type="Class" /></target></connector><connector xmi:idref="auto_gen_thing__-L3bkTJfEfGnvNG6iGafTQ"><properties ea_type="Generalization" direction="Source -&gt; Destination" /><source xmi:idref="_-L3bkTJfEfGnvNG6iGafTQ"><model name="hari:Status" type="Class" /></source><target xmi:idref="ID_AUTO_GENERATED_THING_ROOT"><model name="hari:Thing" type="Class" /></target></connector><connector xmi:idref="auto_gen_thing__-L3blTJfEfGnvNG6iGafTQ"><properties ea_type="Generalization" direction="Source -&gt; Destination" /><source xmi:idref="_-L3blTJfEfGnvNG6iGafTQ"><model name="hari:Level" type="Class" /></source><target xmi:idref="ID_AUTO_GENERATED_THING_ROOT"><model name="hari:Thing" type="Class" /></target></connector><connector xmi:idref="auto_gen_thing__-L3bmjJfEfGnvNG6iGafTQ"><properties ea_type="Generalization" direction="Source -&gt; Destination" /><source xmi:idref="_-L3bmjJfEfGnvNG6iGafTQ"><model name="hari:OntologyProject" type="Class" /></source><target xmi:idref="ID_AUTO_GENERATED_THING_ROOT"><model name="hari:Thing" type="Class" /></target></connector><connector xmi:idref="auto_gen_thing__-L3bpzJfEfGnvNG6iGafTQ"><properties ea_type="Generalization" direction="Source -&gt; Destination" /><source xmi:idref="_-L3bpzJfEfGnvNG6iGafTQ"><model name="hari:ExternalTerm" type="Class" /></source><target xmi:idref="ID_AUTO_GENERATED_THING_ROOT"><model name="hari:Thing" type="Class" /></target></connector><connector xmi:idref="_-LuRmjJfEfGnvNG6iGafTQ"><properties ea_type="Association" direction="Source -&gt; Destination" /><source xmi:idref="_-LuRhDJfEfGnvNG6iGafTQ"><model name="hari:OntologyVersion" type="Class" /></source><target xmi:idref="_-L3bhjJfEfGnvNG6iGafTQ"><model name="hari:ExtensionDecision" type="Class" /><type multiplicity="0..*" /><role name="hari:hasExtension" visibility="Public" /></target></connector><connector xmi:idref="_-LuRnDJfEfGnvNG6iGafTQ"><properties ea_type="Association" direction="Source -&gt; Destination" /><source xmi:idref="_-LuRhDJfEfGnvNG6iGafTQ"><model name="hari:OntologyVersion" type="Class" /></source><target xmi:idref="_-L3bejJfEfGnvNG6iGafTQ"><model name="hari:VersionChange" type="Class" /><type multiplicity="0..*" /><role name="hari:hasChange" visibility="Public" /></target></connector><connector xmi:idref="_-LuRnjJfEfGnvNG6iGafTQ"><properties ea_type="Association" direction="Source -&gt; Destination" /><source xmi:idref="_-LuRhDJfEfGnvNG6iGafTQ"><model name="hari:OntologyVersion" type="Class" /></source><target xmi:idref="_-L3bjzJfEfGnvNG6iGafTQ"><model name="hari:DirectReuseDecision" type="Class" /><type multiplicity="0..*" /><role name="hari:hasReuse" visibility="Public" /></target></connector><connector xmi:idref="_-LuRoDJfEfGnvNG6iGafTQ"><properties ea_type="Association" direction="Source -&gt; Destination" /><source xmi:idref="_-LuRhDJfEfGnvNG6iGafTQ"><model name="hari:OntologyVersion" type="Class" /></source><target xmi:idref="_-LuRhDJfEfGnvNG6iGafTQ"><model name="hari:OntologyVersion" type="Class" /><type multiplicity="0..*" /><role name="hari:hasDependsOn" visibility="Public" /></target></connector><connector xmi:idref="_-L3bcjJfEfGnvNG6iGafTQ"><properties ea_type="Association" direction="Source -&gt; Destination" /><source xmi:idref="_-LuRhDJfEfGnvNG6iGafTQ"><model name="hari:OntologyVersion" type="Class" /></source><target xmi:idref="_-L3bmjJfEfGnvNG6iGafTQ"><model name="hari:OntologyProject" type="Class" /><type multiplicity="1..1" /><role name="hari:isVersionOf" visibility="Public" /></target></connector><connector xmi:idref="_-L3bdjJfEfGnvNG6iGafTQ"><properties ea_type="Association" direction="Source -&gt; Destination" /><source xmi:idref="_-LuRhDJfEfGnvNG6iGafTQ"><model name="hari:OntologyVersion" type="Class" /></source><target xmi:idref="_-L3bkTJfEfGnvNG6iGafTQ"><model name="hari:Status" type="Enumeration" /><type multiplicity="1..1" /><role name="hari:hasStatus" visibility="Public" /></target></connector><connector xmi:idref="_-L3bizJfEfGnvNG6iGafTQ"><properties ea_type="Association" direction="Source -&gt; Destination" /><source xmi:idref="_-L3bhjJfEfGnvNG6iGafTQ"><model name="hari:ExtensionDecision" type="Class" /></source><target xmi:idref="_-L3bpzJfEfGnvNG6iGafTQ"><model name="hari:ExternalTerm" type="Class" /><type multiplicity="1..1" /><role name="hari:hasExtendedClass" visibility="Public" /></target></connector><connector xmi:idref="_-L3bjTJfEfGnvNG6iGafTQ"><properties ea_type="Association" direction="Source -&gt; Destination" /><source xmi:idref="_-L3bhjJfEfGnvNG6iGafTQ"><model name="hari:ExtensionDecision" type="Class" /></source><target xmi:idref="_-L3bpzJfEfGnvNG6iGafTQ"><model name="hari:ExternalTerm" type="Class" /><type multiplicity="1..1" /><role name="hari:hasBaseClass" visibility="Public" /></target></connector><connector xmi:idref="_-L3boTJfEfGnvNG6iGafTQ"><properties ea_type="Association" direction="Source -&gt; Destination" /><source xmi:idref="_-L3bmjJfEfGnvNG6iGafTQ"><model name="hari:OntologyProject" type="Class" /></source><target xmi:idref="_-L3blTJfEfGnvNG6iGafTQ"><model name="hari:Level" type="Enumeration" /><type multiplicity="1..1" /><role name="hari:hasLevel" visibility="Public" /></target></connector><connector xmi:idref="_-L3bqzJfEfGnvNG6iGafTQ"><properties ea_type="Association" direction="Source -&gt; Destination" /><source xmi:idref="_-L3bqDJfEfGnvNG6iGafTQ"><model name="hari:CardinalityExtension" type="Class" /></source><target xmi:idref="_-L3bpzJfEfGnvNG6iGafTQ"><model name="hari:ExternalTerm" type="Class" /><type multiplicity="1..1" /><role name="hari:hasCardinalityChanged" visibility="Public" /></target></connector><connector xmi:idref="_-L3bsDJfEfGnvNG6iGafTQ"><properties ea_type="Association" direction="Source -&gt; Destination" /><source xmi:idref="_-L3brTJfEfGnvNG6iGafTQ"><model name="hari:AttributeExtension" type="Class" /></source><target xmi:idref="_-L3bpzJfEfGnvNG6iGafTQ"><model name="hari:ExternalTerm" type="Class" /><type multiplicity="1..1" /><role name="hari:hasAddedProperty" visibility="Public" /></target></connector><connector xmi:idref="_-L3btTJfEfGnvNG6iGafTQ"><properties ea_type="Association" direction="Source -&gt; Destination" /><source xmi:idref="_-L3bsjJfEfGnvNG6iGafTQ"><model name="hari:ClassReuse" type="Class" /></source><target xmi:idref="_-L3bpzJfEfGnvNG6iGafTQ"><model name="hari:ExternalTerm" type="Class" /><type multiplicity="1..1" /><role name="hari:hasReusedClass" visibility="Public" /></target></connector><connector xmi:idref="_-L3bujJfEfGnvNG6iGafTQ"><properties ea_type="Association" direction="Source -&gt; Destination" /><source xmi:idref="_-L3btzJfEfGnvNG6iGafTQ"><model name="hari:PropertyReuse" type="Class" /></source><target xmi:idref="_-L3bpzJfEfGnvNG6iGafTQ"><model name="hari:ExternalTerm" type="Class" /><type multiplicity="1..1" /><role name="hari:hasReusedProperty" visibility="Public" /></target></connector><connector xmi:idref="_-L3bfTJfEfGnvNG6iGafTQ"><properties ea_type="Generalization" direction="Source -&gt; Destination" /><source xmi:idref="_-L3bfDJfEfGnvNG6iGafTQ"><model name="hari:CardinalityModification" type="Class" /></source><target xmi:idref="_-L3bejJfEfGnvNG6iGafTQ"><model name="hari:VersionChange" type="Class" /></target></connector><connector xmi:idref="_-L3bhDJfEfGnvNG6iGafTQ"><properties ea_type="Generalization" direction="Source -&gt; Destination" /><source xmi:idref="_-L3bgzJfEfGnvNG6iGafTQ"><model name="hari:AttributeAddition" type="Class" /></source><target xmi:idref="_-L3bejJfEfGnvNG6iGafTQ"><model name="hari:VersionChange" type="Class" /></target></connector><connector xmi:idref="_-L3bpjJfEfGnvNG6iGafTQ"><properties ea_type="Generalization" direction="Source -&gt; Destination" /><source xmi:idref="_-L3bpTJfEfGnvNG6iGafTQ"><model name="hari:SemanticExtension" type="Class" /></source><target xmi:idref="_-L3bhjJfEfGnvNG6iGafTQ"><model name="hari:ExtensionDecision" type="Class" /></target></connector><connector xmi:idref="_-L3bqTJfEfGnvNG6iGafTQ"><properties ea_type="Generalization" direction="Source -&gt; Destination" /><source xmi:idref="_-L3bqDJfEfGnvNG6iGafTQ"><model name="hari:CardinalityExtension" type="Class" /></source><target xmi:idref="_-L3bhjJfEfGnvNG6iGafTQ"><model name="hari:ExtensionDecision" type="Class" /></target></connector><connector xmi:idref="_-L3brjJfEfGnvNG6iGafTQ"><properties ea_type="Generalization" direction="Source -&gt; Destination" /><source xmi:idref="_-L3brTJfEfGnvNG6iGafTQ"><model name="hari:AttributeExtension" type="Class" /></source><target xmi:idref="_-L3bhjJfEfGnvNG6iGafTQ"><model name="hari:ExtensionDecision" type="Class" /></target></connector><connector xmi:idref="_-L3bszJfEfGnvNG6iGafTQ"><properties ea_type="Generalization" direction="Source -&gt; Destination" /><source xmi:idref="_-L3bsjJfEfGnvNG6iGafTQ"><model name="hari:ClassReuse" type="Class" /></source><target xmi:idref="_-L3bjzJfEfGnvNG6iGafTQ"><model name="hari:DirectReuseDecision" type="Class" /></target></connector><connector xmi:idref="_-L3buDJfEfGnvNG6iGafTQ"><properties ea_type="Generalization" direction="Source -&gt; Destination" /><source xmi:idref="_-L3btzJfEfGnvNG6iGafTQ"><model name="hari:PropertyReuse" type="Class" /></source><target xmi:idref="_-L3bjzJfEfGnvNG6iGafTQ"><model name="hari:DirectReuseDecision" type="Class" /></target></connector></connectors></xmi:Extension></xmi:XMI>